omdx/__init__.py
omdx/_version.py
omdx/converter.py
omdx/observation.py
omdx/player.py
omdx/data/__init__.py
omdx/data/de421.bsp
omdx/data/hip_main.dat
omdx/data/star_common_names.json
omdx-0.1.2.dist-info/licenses/LICENSE
omdx-0.1.2.dist-info/METADATA
omdx-0.1.2.dist-info/WHEEL
omdx-0.1.2.dist-info/entry_points.txt
omdx-0.1.2.dist-info/top_level.txt
omdx-0.1.2.dist-info/RECORD
