Metadata-Version: 2.4
Name: omdx
Version: 0.1.2
Summary: Open Meteor Data Exchange standard and tools
Home-page: https://github.com/quan787/omdx-project
Author: quan787
Author-email: quan787@qq.com
License: MPL 2.0
Classifier: Programming Language :: Python :: 3
Classifier: License :: OSI Approved :: Mozilla Public License 2.0 (MPL 2.0)
Classifier: Operating System :: OS Independent
Requires-Python: >=3.9
License-File: LICENSE
Requires-Dist: numpy
Requires-Dist: opencv-python
Requires-Dist: astropy
Requires-Dist: pillow
Requires-Dist: skyfield
Dynamic: author
Dynamic: author-email
Dynamic: classifier
Dynamic: description
Dynamic: description-content-type
Dynamic: home-page
Dynamic: license
Dynamic: license-file
Dynamic: requires-dist
Dynamic: requires-python
Dynamic: summary
